betterreplitdb.py
betterreplitdb-0.0.3.dist-info/LICENSE
betterreplitdb-0.0.3.dist-info/METADATA
betterreplitdb-0.0.3.dist-info/WHEEL
betterreplitdb-0.0.3.dist-info/RECORD
