Metadata-Version: 2.1
Name: betterreplitdb
Version: 0.0.3
Summary: Replit DB with a memcache
License: ISC
Author: Dev380
Requires-Python: >=3.8,<4.0
Classifier: License :: OSI Approved
Classifier: Programming Language :: Python :: 3
Classifier: Programming Language :: Python :: 3.8
Classifier: Programming Language :: Python :: 3.9
Classifier: Programming Language :: Python :: 3.10
Classifier: Programming Language :: Python :: 3.11
Requires-Dist: aiohttp (>=3.6.2,<4.0.0)
Requires-Dist: black (>=23.1.0,<24.0.0)
Requires-Dist: requests (>=2.25.1,<3.0.0)
Requires-Dist: twine (>=4.0.2,<5.0.0)
